jettex/__init__.py
jettex/cli.py
jettex/compile.py
jettex/console.py
jettex/install.py
jettex/packages.py
jettex/tlmgr.py
jettex/utils.py
jettex-0.0.2.dist-info/licenses/LICENSE
jettex-0.0.2.dist-info/METADATA
jettex-0.0.2.dist-info/WHEEL
jettex-0.0.2.dist-info/entry_points.txt
jettex-0.0.2.dist-info/top_level.txt
jettex-0.0.2.dist-info/RECORD
