Metadata-Version: 2.4
Name: jettex
Version: 0.0.2
Summary: A lightweight Python wrapper for TinyTeX - blazing-fast install, compile, and auto-manage packages
Author-email: Gauransh <gauranshk21@gmail.com>
License: MIT
Project-URL: Homepage, https://github.com/gauranshkumar/jettex
Project-URL: Documentation, https://jettex.readthedocs.io/en/latest/
Project-URL: Repository, https://github.com/gauranshkumar/jettex
Project-URL: Issues, https://github.com/gauranshkumar/jettex/issues
Keywords: latex,tinytex,tex,pdf,typesetting,document
Classifier: Development Status :: 4 - Beta
Classifier: Intended Audience :: Developers
Classifier: Intended Audience :: Science/Research
Classifier: License :: OSI Approved :: MIT License
Classifier: Operating System :: OS Independent
Classifier: Programming Language :: Python :: 3
Classifier: Programming Language :: Python :: 3.8
Classifier: Programming Language :: Python :: 3.9
Classifier: Programming Language :: Python :: 3.10
Classifier: Programming Language :: Python :: 3.11
Classifier: Programming Language :: Python :: 3.12
Classifier: Topic :: Text Processing :: Markup :: LaTeX
Requires-Python: >=3.8
License-File: LICENSE
Requires-Dist: requests>=2.25.0
Requires-Dist: rich>=13.0.0
Provides-Extra: dev
Requires-Dist: pytest>=7.0.0; extra == "dev"
Requires-Dist: pytest-cov>=4.0.0; extra == "dev"
Requires-Dist: ruff>=0.1.0; extra == "dev"
Provides-Extra: docs
Requires-Dist: mkdocs>=1.5.0; extra == "docs"
Requires-Dist: mkdocs-material>=9.0.0; extra == "docs"
Requires-Dist: mkdocstrings[python]>=0.24.0; extra == "docs"
Dynamic: license-file
